odoo10_addon_account_analytic_no_lines-10.0.1.0.0.99.dev33-nspkg.pth
odoo/addons/account_analytic_no_lines/README.rst
odoo/addons/account_analytic_no_lines/__init__.py
odoo/addons/account_analytic_no_lines/__manifest__.py
odoo/addons/account_analytic_no_lines/i18n/account_analytic_no_lines.pot
odoo/addons/account_analytic_no_lines/i18n/ca.po
odoo/addons/account_analytic_no_lines/i18n/cs_CZ.po
odoo/addons/account_analytic_no_lines/i18n/de.po
odoo/addons/account_analytic_no_lines/i18n/el_GR.po
odoo/addons/account_analytic_no_lines/i18n/es.po
odoo/addons/account_analytic_no_lines/i18n/es_EC.po
odoo/addons/account_analytic_no_lines/i18n/es_MX.po
odoo/addons/account_analytic_no_lines/i18n/fi.po
odoo/addons/account_analytic_no_lines/i18n/fr.po
odoo/addons/account_analytic_no_lines/i18n/gu_IN.po
odoo/addons/account_analytic_no_lines/i18n/hi_IN.po
odoo/addons/account_analytic_no_lines/i18n/hr.po
odoo/addons/account_analytic_no_lines/i18n/hr_HR.po
odoo/addons/account_analytic_no_lines/i18n/nl.po
odoo/addons/account_analytic_no_lines/i18n/nl_NL.po
odoo/addons/account_analytic_no_lines/i18n/pt.po
odoo/addons/account_analytic_no_lines/i18n/pt_BR.po
odoo/addons/account_analytic_no_lines/i18n/ru.po
odoo/addons/account_analytic_no_lines/i18n/sk_SK.po
odoo/addons/account_analytic_no_lines/i18n/sl.po
odoo/addons/account_analytic_no_lines/i18n/zh_CN.po
odoo/addons/account_analytic_no_lines/models/__init__.py
odoo/addons/account_analytic_no_lines/models/account_analytic_account.py
odoo/addons/account_analytic_no_lines/models/account_invoice.py
odoo/addons/account_analytic_no_lines/models/account_move_line.py
odoo/addons/account_analytic_no_lines/security/data_account_analytic_group.xml
odoo/addons/account_analytic_no_lines/static/description/icon.png
odoo/addons/account_analytic_no_lines/tests/__init__.py
odoo/addons/account_analytic_no_lines/tests/test_account_analytic_no_lines.py
odoo/addons/account_analytic_no_lines/views/account_analytic.xml
odoo10_addon_account_analytic_no_lines-10.0.1.0.0.99.dev33.dist-info/METADATA
odoo10_addon_account_analytic_no_lines-10.0.1.0.0.99.dev33.dist-info/WHEEL
odoo10_addon_account_analytic_no_lines-10.0.1.0.0.99.dev33.dist-info/namespace_packages.txt
odoo10_addon_account_analytic_no_lines-10.0.1.0.0.99.dev33.dist-info/top_level.txt
odoo10_addon_account_analytic_no_lines-10.0.1.0.0.99.dev33.dist-info/RECORD
